{
  "date": "2026-06-05",
  "time": "2026-06-05-18-30-11",
  "weekday": "Fri",
  "epoch": 1780684211,
  "random": 107503,
  "approver_username": "orangehrmlahiru",
  "repos": [
    {
      "name": "mesh-runner-102203",
      "full_name": "lahirunirmalx/mesh-runner-102203",
      "creation_status": "created",
      "collaborator_status": "invited",
      "pr_number": 1,
      "pr_approved": true,
      "pr_merged": true,
      "issues": [
        2,
        3
      ]
    }
  ],
  "issue_cleanup": {
    "checked_repos": 3,
    "closed": []
  }
}
