{
  "date": "2026-07-11",
  "time": "2026-07-11-02-30-42",
  "weekday": "Sat",
  "epoch": 1783737042,
  "random": 555326,
  "approver_username": "orangehrmlahiru",
  "repos": [
    {
      "name": "queue-proxy-565578",
      "full_name": "lahirunirmalx/queue-proxy-565578",
      "creation_status": "created",
      "collaborator_status": "invited",
      "pr_number": 1,
      "pr_approved": true,
      "pr_merged": true,
      "issues": [
        2,
        3
      ]
    },
    {
      "name": "tracker-flux-349586",
      "full_name": "lahirunirmalx/tracker-flux-349586",
      "creation_status": "created",
      "collaborator_status": "invited",
      "pr_number": 1,
      "pr_approved": true,
      "pr_merged": true,
      "issues": [
        4,
        2,
        6,
        5,
        3
      ]
    },
    {
      "name": "rune-queue-625713",
      "full_name": "lahirunirmalx/rune-queue-625713",
      "creation_status": "created",
      "collaborator_status": "invited",
      "pr_number": 1,
      "pr_approved": true,
      "pr_merged": true,
      "issues": [
        2,
        4,
        6,
        3,
        5
      ]
    }
  ],
  "issue_cleanup": {
    "checked_repos": 3,
    "closed": [
      {
        "repo": "lahirunirmalx/listener-cache-158687",
        "issue": 5
      },
      {
        "repo": "lahirunirmalx/listener-cache-158687",
        "issue": 3
      }
    ]
  }
}
