{
  "date": "2026-07-01",
  "time": "2026-07-01-22-30-30",
  "weekday": "Wed",
  "epoch": 1782945030,
  "random": 637035,
  "approver_username": "orangehrmlahiru",
  "repos": [
    {
      "name": "forge-orbit-369211",
      "full_name": "lahirunirmalx/forge-orbit-369211",
      "creation_status": "created",
      "collaborator_status": "invited",
      "pr_number": 1,
      "pr_approved": true,
      "pr_merged": true,
      "issues": [
        2,
        3
      ]
    },
    {
      "name": "cache-profiler-681901",
      "full_name": "lahirunirmalx/cache-profiler-681901",
      "creation_status": "created",
      "collaborator_status": "invited",
      "pr_number": 1,
      "pr_approved": true,
      "pr_merged": false,
      "issues": [
        2,
        6,
        5,
        3,
        4
      ]
    },
    {
      "name": "daemon-sampler-537332",
      "full_name": "lahirunirmalx/daemon-sampler-537332",
      "creation_status": "created",
      "collaborator_status": "invited",
      "pr_number": 1,
      "pr_approved": true,
      "pr_merged": false,
      "issues": [
        3,
        4,
        2
      ]
    }
  ],
  "issue_cleanup": {
    "checked_repos": 3,
    "closed": []
  }
}
