{
  "date": "2026-06-19",
  "time": "2026-06-19-10-30-19",
  "weekday": "Fri",
  "epoch": 1781865019,
  "random": 405582,
  "approver_username": "orangehrmlahiru",
  "repos": [
    {
      "name": "linter-monitor-961821",
      "full_name": "lahirunirmalx/linter-monitor-961821",
      "creation_status": "created",
      "collaborator_status": "invited",
      "pr_number": 1,
      "pr_approved": true,
      "pr_merged": true,
      "issues": [
        2
      ]
    },
    {
      "name": "router-indexer-982613",
      "full_name": "lahirunirmalx/router-indexer-982613",
      "creation_status": "created",
      "collaborator_status": "invited",
      "pr_number": 1,
      "pr_approved": true,
      "pr_merged": true,
      "issues": [
        2,
        3,
        4
      ]
    },
    {
      "name": "proxy-pipeline-913964",
      "full_name": "lahirunirmalx/proxy-pipeline-913964",
      "creation_status": "created",
      "collaborator_status": "invited",
      "pr_number": 1,
      "pr_approved": true,
      "pr_merged": true,
      "issues": [
        3,
        2,
        4
      ]
    }
  ],
  "issue_cleanup": {
    "checked_repos": 3,
    "closed": []
  }
}
