{
  "date": "2026-07-01",
  "time": "2026-07-01-02-30-28",
  "weekday": "Wed",
  "epoch": 1782873028,
  "random": 865930,
  "approver_username": "orangehrmlahiru",
  "repos": [
    {
      "name": "spark-pipeline-743716",
      "full_name": "lahirunirmalx/spark-pipeline-743716",
      "creation_status": "created",
      "collaborator_status": "invited",
      "pr_number": 1,
      "pr_approved": true,
      "pr_merged": true,
      "issues": [
        4,
        2,
        3
      ]
    },
    {
      "name": "rune-flux-971794",
      "full_name": "lahirunirmalx/rune-flux-971794",
      "creation_status": "created",
      "collaborator_status": "invited",
      "pr_number": 1,
      "pr_approved": true,
      "pr_merged": true,
      "issues": [
        2,
        3
      ]
    },
    {
      "name": "fetcher-core-452399",
      "full_name": "lahirunirmalx/fetcher-core-452399",
      "creation_status": "created",
      "collaborator_status": "invited",
      "pr_number": 1,
      "pr_approved": true,
      "pr_merged": true,
      "issues": [
        2,
        3,
        5,
        4
      ]
    }
  ],
  "issue_cleanup": {
    "checked_repos": 3,
    "closed": [
      {
        "repo": "lahirunirmalx/pixel-router-801564",
        "issue": 5
      },
      {
        "repo": "lahirunirmalx/pixel-router-801564",
        "issue": 4
      },
      {
        "repo": "lahirunirmalx/pixel-router-801564",
        "issue": 3
      }
    ]
  }
}
